[
  {
    "Project": "TrueTrading / Archblock",
    "Estimated Liabilities": "$35M",
    "Status": "TrueFi pool default; recovery ongoing",
    "Type": "Borrowing Pool"
  },
  {
    "Project": "Bitconnect",
    "Estimated Liabilities": "N/A",
    "Status": "SEC/DOJ seized"
  },
  {
    "Project": "OneCoin",
    "Estimated Liabilities": "$4B+",
    "Status": "Massive global scam"
  },
  {
    "Project": "Centra Tech",
    "Estimated Liabilities": "$25M+",
    "Status": "SEC redemptions"
  },
  {
    "Project": "Confido",
    "Estimated Liabilities": "N/A",
    "Status": "Exit scam"
  },
  {
    "Project": "PlexCoin",
    "Estimated Liabilities": "$10M",
    "Status": "SEC seizure"
  },
  {
    "Project": "Benebit",
    "Estimated Liabilities": "N/A",
    "Status": "Exit scam"
  },
  {
    "Project": "LoopX",
    "Estimated Liabilities": "N/A",
    "Status": "Exit scam"
  },
  {
    "Project": "Bitcard",
    "Estimated Liabilities": "N/A",
    "Status": "Exit scam"
  },
  {
    "Project": "Prodeum",
    "Estimated Liabilities": "N/A",
    "Status": "Exit scam"
  },
  {
    "Project": "MyBit",
    "Estimated Liabilities": "N/A",
    "Status": "Token flop"
  },
  {
    "Project": "BitClave",
    "Estimated Liabilities": "$25M",
    "Status": "SEC enforcement; Fair Fund ongoing"
  },
  {
    "Project": "Ripple (XRP)",
    "Estimated Liabilities": "N/A",
    "Status": "SEC litigation ongoing; potential Fair Fund"
  },
  {
    "Project": "Block.one (EOS)",
    "Estimated Liabilities": "$24M settlement",
    "Status": "SEC settlement in 2019; no Fair Fund announced"
  },
  {
    "Project": "Telegram (TON)",
    "Estimated Liabilities": "$1.2B return ordered",
    "Status": "SEC settlement; funds returned"
  },
  {
    "Project": "Sparkster",
    "Estimated Liabilities": "$35M",
    "Status": "SEC settled; funds being returned via Fair Fund"
  },
  {
    "Project": "Trade Coin Club",
    "Estimated Liabilities": "$295M est.",
    "Status": "SEC enforcement; early stage"
  },
  {
    "Project": "Nexo Capital",
    "Estimated Liabilities": "$45M",
    "Status": "SEC + state AG settlements; likely Fair Fund"
  },
  {
    "Project": "Recoin & DRC World",
    "Estimated Liabilities": "N/A",
    "Status": "SEC fraud enforcement; possible Fair Fund"
  },
  {
    "Project": "ICOBox",
    "Estimated Liabilities": "$16M",
    "Status": "SEC judgment; recovery uncertain"
  },
  {
    "Project": "LBRY",
    "Estimated Liabilities": "N/A",
    "Status": "SEC case lost on appeal; unclear recovery"
  },
  {
    "Project": "Library Credits",
    "Estimated Liabilities": "N/A",
    "Status": "Same as LBRY"
  },
  {
    "Project": "Paragon & AirFox",
    "Estimated Liabilities": "$270K combined",
    "Status": "Fair Funds completed"
  },
  {
    "Project": "FTX",
    "Estimated Liabilities": "$8B+",
    "Status": "Bankruptcy"
  },
  {
    "Project": "Celsius Network",
    "Estimated Liabilities": "$5B+",
    "Status": "Bankruptcy, plan confirmed"
  },
  {
    "Project": "Three Arrows Capital (3AC)",
    "Estimated Liabilities": "$3B+",
    "Status": "Liquidation (BVI)"
  },
  {
    "Project": "Genesis Global",
    "Estimated Liabilities": "$3.5B+",
    "Status": "Chapter 11"
  },
  {
    "Project": "Voyager Digital",
    "Estimated Liabilities": "$1.3B",
    "Status": "Chapter 11"
  },
  {
    "Project": "BlockFi",
    "Estimated Liabilities": "$1B–$2B",
    "Status": "Chapter 11"
  },
  {
    "Project": "Mt. Gox",
    "Estimated Liabilities": "$3.5B",
    "Status": "Rehabilitation"
  },
  {
    "Project": "Cred Inc.",
    "Estimated Liabilities": "$500M",
    "Status": "Chapter 11"
  },
  {
    "Project": "CoinFLEX",
    "Estimated Liabilities": "$100M+",
    "Status": "Restructuring"
  },
  {
    "Project": "Zipmex",
    "Estimated Liabilities": "$50M–100M",
    "Status": "Restructuring (SG/TH)"
  },
  {
    "Project": "QuadrigaCX",
    "Estimated Liabilities": "$200M CAD",
    "Status": "Bankruptcy"
  },
  {
    "Project": "BitGrail",
    "Estimated Liabilities": "$170M",
    "Status": "Italian liquidation"
  },
  {
    "Project": "Terra / Anchor",
    "Estimated Liabilities": "Unknown",
    "Status": "No bankruptcy; class action"
  },
  {
    "Project": "Civic",
    "Estimated Liabilities": "Unknown",
    "Status": "Token collapse"
  },
  {
    "Project": "SafeMoon",
    "Estimated Liabilities": "Unknown",
    "Status": "SEC enforcement"
  },
  {
    "Project": "Hodlnaut",
    "Estimated Liabilities": "Unknown",
    "Status": "Singapore liquidation"
  },
  {
    "Project": "Babel Finance",
    "Estimated Liabilities": "Unknown",
    "Status": "Insolvent; restructuring"
  },
  {
    "Project": "Amber Group",
    "Estimated Liabilities": "Unknown",
    "Status": "Collapse under review"
  },
  {
    "Project": "Cryptopia",
    "Estimated Liabilities": "$100M+",
    "Status": "New Zealand liquidation"
  },
  {
    "Project": "BTC-e / WEX",
    "Estimated Liabilities": "$500M+ (est.)",
    "Status": "Seized, unclear path"
  },
  {
    "Project": "Maple Finance",
    "Estimated Liabilities": "Unknown",
    "Status": "Credit defaults"
  },
  {
    "Project": "Mirror Protocol",
    "Estimated Liabilities": "Unknown",
    "Status": "Class actions (U.S.)"
  }
]
